setup.py
opuslib/__init__.py
opuslib/classes.py
opuslib/constants.py
opuslib/exceptions.py
opuslib.egg-info/PKG-INFO
opuslib.egg-info/SOURCES.txt
opuslib.egg-info/dependency_links.txt
opuslib.egg-info/not-zip-safe
opuslib.egg-info/top_level.txt
opuslib/api/__init__.py
opuslib/api/constants.py
opuslib/api/ctl.py
opuslib/api/decoder.py
opuslib/api/encoder.py
opuslib/api/info.py