Metadata-Version: 1.1
Name: opuslib
Version: 1.1.0
Summary: Python bindings to the libopus, IETF low-delay audio codec
Home-page: https://github.com/onbeep/opuslib
Author: Orion Labs, Inc.
Author-email: code@orionlabs.co
License: BSD 3-Clause License
Platform: UNKNOWN
Classifier: Development Status :: 1 - Planning
Classifier: Intended Audience :: Developers
Classifier: License :: OSI Approved :: BSD License
Classifier: Operating System :: OS Independent
Classifier: Programming Language :: Python
Classifier: Programming Language :: Python :: 2.5
Classifier: Programming Language :: Python :: 2.6
Classifier: Programming Language :: Python :: 2.7
Classifier: Topic :: Software Development :: Libraries
Classifier: Topic :: Multimedia :: Sound/Audio :: Conversion
